emic/__init__.py
emic/pipeline.py
emic/analysis/__init__.py
emic/analysis/measures.py
emic/analysis/summary.py
emic/inference/__init__.py
emic/inference/errors.py
emic/inference/protocol.py
emic/inference/result.py
emic/inference/cssr/__init__.py
emic/inference/cssr/algorithm.py
emic/inference/cssr/config.py
emic/inference/cssr/partition.py
emic/inference/cssr/suffix_tree.py
emic/inference/cssr/tests.py
emic/output/__init__.py
emic/output/diagram.py
emic/output/latex.py
emic/output/serialization.py
emic/sources/__init__.py
emic/sources/base.py
emic/sources/protocol.py
emic/sources/empirical/__init__.py
emic/sources/empirical/sequence_data.py
emic/sources/synthetic/__init__.py
emic/sources/synthetic/biased_coin.py
emic/sources/synthetic/even_process.py
emic/sources/synthetic/golden_mean.py
emic/sources/synthetic/periodic.py
emic/sources/transforms/__init__.py
emic/sources/transforms/skip.py
emic/sources/transforms/take.py
emic/types/__init__.py
emic/types/alphabet.py
emic/types/machine.py
emic/types/probability.py
emic/types/states.py
emic-0.1.1.dist-info/METADATA
emic-0.1.1.dist-info/WHEEL
emic-0.1.1.dist-info/licenses/LICENSE
emic-0.1.1.dist-info/RECORD
