Metadata-Version: 2.4
Name: emic
Version: 0.1.1
Summary: Epsilon Machine Inference & Characterization - A framework for computational mechanics
Project-URL: Homepage, https://github.com/johnazariah/emic
Project-URL: Documentation, https://github.com/johnazariah/emic#readme
Project-URL: Repository, https://github.com/johnazariah/emic
Project-URL: Issues, https://github.com/johnazariah/emic/issues
Author-email: John Azariah <john.azariah@student.uts.edu.au>
License-Expression: MIT
License-File: LICENSE
Keywords: causal-states,complexity,computational-mechanics,emergence,epsilon-machine,stochastic-processes
Classifier: Development Status :: 3 - Alpha
Classifier: Intended Audience :: Science/Research
Classifier: License :: OSI Approved :: MIT License
Classifier: Programming Language :: Python :: 3
Classifier: Programming Language :: Python :: 3.11
Classifier: Programming Language :: Python :: 3.12
Classifier: Topic :: Scientific/Engineering
Classifier: Topic :: Scientific/Engineering :: Mathematics
Classifier: Typing :: Typed
Requires-Python: >=3.11
Requires-Dist: graphviz>=0.21
Requires-Dist: numpy>=2.4.1
Requires-Dist: scipy>=1.17.0
Provides-Extra: all
Requires-Dist: graphviz>=0.20; extra == 'all'
Requires-Dist: mkdocs-material>=9.0; extra == 'all'
Requires-Dist: mkdocs>=1.5; extra == 'all'
Requires-Dist: mkdocstrings[python]>=0.24; extra == 'all'
Provides-Extra: docs
Requires-Dist: mkdocs-material>=9.0; extra == 'docs'
Requires-Dist: mkdocs>=1.5; extra == 'docs'
Requires-Dist: mkdocstrings[python]>=0.24; extra == 'docs'
Provides-Extra: viz
Requires-Dist: graphviz>=0.20; extra == 'viz'
